{"dependencies":[{"name":"./elements","loc":{"line":1,"column":30}}],"generated":{"js":"\"use strict\";\n\nObject.defineProperty(exports, \"__esModule\", {\n  value: true\n});\n\nvar _elements = require(\"./elements\");\n\nvar _elements2 = _interopRequireDefault(_elements);\n\nfunction _interopRequireDefault(obj) { return obj && obj.__esModule ? obj : { default: obj }; }\n\nlet state = '';\n// default componenets\nlet colors = [\n// colors\n{\n  parent: 'component_app_colors',\n  id: '',\n  classList: '',\n  innerHTML: '\\\n   ' + _elements2.default.element_colors() + '\\\n'\n}];\nlet stages = [\n// colors\n{\n  parent: 'component_app_stages',\n  id: '',\n  classList: '',\n  innerHTML: '\\\n   ' + _elements2.default.element_grid_cross() + '\\\n   \\\n   ' + _elements2.default.element_grid_depth_90() + '\\\n   \\\n   ' + _elements2.default.element_accent_noise() + '\\\n   \\\n   ' + _elements2.default.element_effect_vignette() + '\\\n   \\\n   ' + _elements2.default.component_app_stage_enneagon() + '\\\n   \\\n   ' + _elements2.default.stage_load_verticle() + '\\\n   \\\n   ' + _elements2.default.stage_load_horizontal() + '\\\n'\n}];\nlet particles = [{\n  parent: 'component_app_particles',\n  id: '',\n  classList: '',\n  innerHTML: '\\\n   ' + _elements2.default.element_particles() + '\\\n\\\n'\n}];\nlet interactions = [{\n  parent: 'component_app_interactions',\n  id: '',\n  classList: '',\n  innerHTML: '\\\n   ' + _elements2.default.element_interaction_player() + '\\\n   \\\n   <div id=\"logo_opacity\" class=\"position_absolute left_0 top_0 right_0 bottom_0 margin_auto width_50 height_50 overflow_hidden float_left opacity_02 gui_logo_combo_frame_1\">\\\n   </div>\\\n   \\\n'\n}];\nlet gui = [{\n  parent: 'component_app_gui',\n  id: '',\n  classList: '',\n  innerHTML: '\\\n         \\\n         <div id=\"component_modal_scroll_fixed_feature_4\" class=\"width_100 height_100vh float_left position_relative display opacity_1 overflow_hidden\">\\\n           ' + _elements2.default.element_fold() + '\\\n         </div>\\\n         \\\n      '\n}, {\n  parent: 'component_app_gui',\n  id: '',\n  classList: '',\n  innerHTML: _elements2.default.element_gui_scroll_y()\n}, {\n  parent: 'component_app_gui_scroll_y',\n  id: 'wp_component_app_wp',\n  classList: ' display opacity_1 easing_01 width_100 position_relative margin_auto',\n  innerHTML: _elements2.default.wp_home_posts()\n}, {\n  parent: 'component_app_gui',\n  id: '',\n  classList: '',\n  innerHTML: '\\\n         \\\n         <div id=\"component_modal_scroll_fixed_feature_4\" class=\"width_100 height_100vh float_left position_relative display opacity_1 overflow_hidden\">\\\n           ' + _elements2.default.element_guis() + '\\\n         </div>\\\n         \\\n      '\n}];\nlet modals = [\n// modals\n{\n  parent: 'component_app_modals',\n  id: '',\n  classList: '',\n  innerHTML: '\\\n   \\\n   ' + _elements2.default.element_pop_top + '\\\n   ' + _elements2.default.element_pop_left + '\\\n   ' + _elements2.default.element_pop_bottom + '\\\n   ' + _elements2.default.element_pop_right + '\\\n   \\\n   ' + _elements2.default.element_page_top + '\\\n   ' + _elements2.default.element_page_left + '\\\n   ' + _elements2.default.element_page_bottom + '\\\n   ' + _elements2.default.element_page_right + '\\\n   \\\n   ' + _elements2.default.element_menu_top + '\\\n   ' + _elements2.default.element_menu_left + '\\\n   ' + _elements2.default.element_menu_bottom + '\\\n   ' + _elements2.default.element_menu_right + '\\\n   \\\n   ' + _elements2.default.element_morph_top + '\\\n   ' + _elements2.default.element_morph_left + '\\\n   ' + _elements2.default.element_morph_bottom + '\\\n   ' + _elements2.default.element_morph_right + '\\\n   \\\n   ' + _elements2.default.element_fade_top + '\\\n   ' + _elements2.default.element_fade_left + '\\\n   ' + _elements2.default.element_fade_bottom + '\\\n   ' + _elements2.default.element_fade_right + '\\\n   \\\n   ' + _elements2.default.element_gradient_top + '\\\n   ' + _elements2.default.element_gradient_left + '\\\n   ' + _elements2.default.element_gradient_bottom + '\\\n   ' + _elements2.default.element_gradient_right + '\\\n   \\\n   ' + _elements2.default.element_corner_top + '\\\n   ' + _elements2.default.element_corner_left + '\\\n   ' + _elements2.default.element_corner_bottom + '\\\n   ' + _elements2.default.element_corner_right + '\\\n   \\\n   ' + _elements2.default.element_overlay_top + '\\\n   ' + _elements2.default.element_overlay_left + '\\\n   ' + _elements2.default.element_overlay_bottom + '\\\n   ' + _elements2.default.element_overlay_right + '\\\n   \\\n   ' + _elements2.default.element_nav_top + '\\\n   ' + _elements2.default.element_nav_left + '\\\n   ' + _elements2.default.element_nav_bottom + '\\\n   ' + _elements2.default.element_nav_right + '\\\n   \\\n'\n}];\nexports.default = {\n  colors,\n  stages,\n  particles,\n  interactions,\n  gui,\n  modals\n};"},"hash":"4f69fd9616edabcec3e12abf9e3fa296"}